sqla_history/__init__.py
sqla_history/base.py
sqla_history/context.py
sqla_history/dto.py
sqla_history/event_handlers.py
sqla_history/not_set.py
sqla_history/py.typed
sqla_history/stmt_builder.py
sqla_history/types_.py
sqla_history/utils.py
sqla_history-0.5.0.dist-info/METADATA
sqla_history-0.5.0.dist-info/WHEEL
sqla_history-0.5.0.dist-info/RECORD
